{
  "code": "0",
  "message": "success",
  "detail": "",
  "data": {
    "reserveBanner": [],
    "reserveList": [
      {
        "adsName": "reserveList",
        "content": [
          {
            "id": 0,
            "description": null,
            "picUrl": "http://p.yhres.com/topic/2017/02/28/156745_1488294799590.jpg-q75",
            "sPicUrl": "http://p.yhres.com/topic/2017/02/28/156745_1488294799590.jpg-ssq75",
            "title": "松露的正确品鉴方法",
            "linkUrl": "/topic/4273",
            "schemeUrl": "yhouse://topic/4273",
            "linkName": "TOPIC",
            "linkType": 6,
            "pvUrl": null,
            "linkId": 4273,
            "xsort": 1,
            "actual": false
          },
          {
            "id": 0,
            "description": null,
            "picUrl": "http://p.yhres.com/topic/2017/01/13/156957_1484273477653.jpg-q75",
            "sPicUrl": "http://p.yhres.com/topic/2017/01/13/156957_1484273477653.jpg-ssq75",
            "title": "迷你小厨师的3D餐桌厨艺秀登陆武汉",
            "linkUrl": "/topic/3633",
            "schemeUrl": "yhouse://topic/3633",
            "linkName": "TOPIC",
            "linkType": 6,
            "pvUrl": null,
            "linkId": 3633,
            "xsort": 3,
            "actual": false
          },
          {
            "id": 1663,
            "description": null,
            "picUrl": "http://p.yhres.com/file/2016/11/18/1479444580111578.jpg-q75",
            "sPicUrl": "http://p.yhres.com/file/2016/11/18/1479444580111578.jpg-ssq75",
            "title": "兰芝美丽上扬课堂",
            "linkUrl": "http://www.laneige.com/cn/zh/main.html",
            "schemeUrl": "yhouse://web?title=%E5%85%B0%E8%8A%9D%E7%BE%8E%E4%B8%BD%E4%B8%8A%E6%89%AC%E8%AF%BE%E5%A0%82&url=http%3A%2F%2Fwww.laneige.com%2Fcn%2Fzh%2Fmain.html&shareIcon=http%3A%2F%2Fp.yhres.com%2Ffile%2F2016%2F11%2F18%2F1479444580111578.jpg-ssq75&shareTitle=%E5%85%B0%E8%8A%9D%E7%BE%8E%E4%B8%BD%E4%B8%8A%E6%89%AC%E8%AF%BE%E5%A0%82&shareDesc=",
            "linkName": "HTML5",
            "linkType": 4,
            "pvUrl": "",
            "linkId": null,
            "xsort": 4,
            "actual": false
          },
          {
            "id": 0,
            "description": null,
            "picUrl": "http://p.yhres.com/topic/2017/02/21/156745_1487681673991.jpg-q75",
            "sPicUrl": "http://p.yhres.com/topic/2017/02/21/156745_1487681673991.jpg-ssq75",
            "title": "简单不粗暴的选一份工作餐",
            "linkUrl": "/topic/4251",
            "schemeUrl": "yhouse://topic/4251",
            "linkName": "TOPIC",
            "linkType": 6,
            "pvUrl": null,
            "linkId": 4251,
            "xsort": 5,
            "actual": false
          },
          {
            "id": 0,
            "description": null,
            "picUrl": "http://p.yhres.com/topic/2017/02/21/156745_1487652066268.jpg-q75",
            "sPicUrl": "http://p.yhres.com/topic/2017/02/21/156745_1487652066268.jpg-ssq75",
            "title": "乘风破浪踏遍江城绝佳吃喝玩乐地",
            "linkUrl": "/topic/4237",
            "schemeUrl": "yhouse://topic/4237",
            "linkName": "TOPIC",
            "linkType": 6,
            "pvUrl": null,
            "linkId": 4237,
            "xsort": 6,
            "actual": false
          },
          {
            "id": 0,
            "description": null,
            "picUrl": "http://p.yhres.com/topic/2017/02/20/156745_1487554680710.jpg-q75",
            "sPicUrl": "http://p.yhres.com/topic/2017/02/20/156745_1487554680710.jpg-ssq75",
            "title": "茶餐厅的灵魂搭档居然是TA",
            "linkUrl": "/topic/4137",
            "schemeUrl": "yhouse://topic/4137",
            "linkName": "TOPIC",
            "linkType": 6,
            "pvUrl": null,
            "linkId": 4137,
            "xsort": 7,
            "actual": false
          }
        ],
        "position": 1
      }
    ],
    "bundle": []
  }
}